[{"Name": "Marcel Ag\u00fceros", "Title": "Associate Professor, Astronomy", "url": "https://www.astro.columbia.edu/content/marcel-agueros", "Research Summary": null, "Research Embedding": null}, {"Name": "James Applegate", "Title": "Professor, Astronomy", "url": "https://www.astro.columbia.edu/content/james-applegate", "Research Summary": null, "Research Embedding": null}, {"Name": "Greg Bryan", "Title": "Professor, Astronomy; Chair, Astronomy", "url": "https://www.astro.columbia.edu/content/greg-bryan", "Research Summary": null, "Research Embedding": null}, {"Name": "Zoltan Haiman", "Title": "Professor, Astronomy; Professor, Physics", "url": "https://www.astro.columbia.edu/content/zoltan-haiman", "Research Summary": null, "Research Embedding": null}, {"Name": "Jules Halpern", "Title": "Professor, Astronomy", "url": "https://www.astro.columbia.edu/content/jules-halpern", "Research Summary": null, "Research Embedding": null}, {"Name": "David Helfand", "Title": "Professor, Astronomy", "url": "https://www.astro.columbia.edu/content/david-helfand", "Research Summary": null, "Research Embedding": null}, {"Name": "Jane Huang", "Title": "Assistant Professor, Astronomy", "url": "https://www.astro.columbia.edu/content/jane-huang", "Research Summary": null, "Research Embedding": null}, {"Name": "Kathryn Johnston", "Title": "Professor, Astronomy", "url": "https://www.astro.columbia.edu/content/kathryn-johnston", "Research Summary": null, "Research Embedding": null}, {"Name": "David Kipping", "Title": "Assistant Professor, Astronomy", "url": "https://www.astro.columbia.edu/content/david-kipping", "Research Summary": null, "Research Embedding": null}, {"Name": "Melissa Ness", "Title": "Assistant Professor, Astronomy", "url": "https://www.astro.columbia.edu/content/melissa-ness", "Research Summary": null, "Research Embedding": null}, {"Name": "Jeremiah Ostriker", "Title": "Professor, Astronomy", "url": "https://www.astro.columbia.edu/content/jeremiah-ostriker", "Research Summary": null, "Research Embedding": null}, {"Name": "Frederik Paerels", "Title": "Professor, Astronomy; Director of Undergraduate Studies, Astronomy", "url": "https://www.astro.columbia.edu/content/frederik-paerels", "Research Summary": null, "Research Embedding": null}, {"Name": "Joseph Patterson", "Title": "Professor, Astronomy", "url": "https://www.astro.columbia.edu/content/joseph-patterson", "Research Summary": null, "Research Embedding": null}, {"Name": "Mary Putman", "Title": "Professor, Astronomy", "url": "https://www.astro.columbia.edu/content/mary-putman", "Research Summary": null, "Research Embedding": null}, {"Name": "David Schiminovich", "Title": "Professor, Astronomy; Co-Director, Astrophysics Lab", "url": "https://www.astro.columbia.edu/content/david-schiminovich", "Research Summary": null, "Research Embedding": null}, {"Name": "Lorenzo Sironi", "Title": "Assistant Professor, Astronomy; Director of Graduate Studies, Astronomy", "url": "https://www.astro.columbia.edu/content/lorenzo-sironi", "Research Summary": null, "Research Embedding": null}, {"Name": "Jacqueline van Gorkom", "Title": "Rutherfurd Professor, Astronomy", "url": "https://www.astro.columbia.edu/content/jacqueline-van-gorkom", "Research Summary": null, "Research Embedding": null}, {"Name": "Malvin A. Ruderman", "Title": "Centennial Professor, Physics", "url": "https://www.astro.columbia.edu/content/malvin-ruderman", "Research Summary": null, "Research Embedding": null}, {"Name": "Michael Allison", "Title": "Adjunct Professor, Astronomy", "url": "https://www.astro.columbia.edu/content/michael-allison", "Research Summary": null, "Research Embedding": null}, {"Name": "Ruth Angus", "Title": "Adjunct Asst. Professor, Astronomy; Assistant Curator, AMNH", "url": "https://www.astro.columbia.edu/content/ruth-angus", "Research Summary": null, "Research Embedding": null}, {"Name": "Elena Aprile", "Title": "Centennial Professor, Physics", "url": "https://www.astro.columbia.edu/content/elena-aprile", "Research Summary": null, "Research Embedding": null}, {"Name": "Andrei M. Beloborodov", "Title": "Professor, Physics", "url": "https://www.astro.columbia.edu/content/andrei-m-beloborodov", "Research Summary": null, "Research Embedding": null}, {"Name": "Charles Hailey", "Title": "Pupin Professor of Physics; Co-Director, Astrophysics Laboratory", "url": "https://www.astro.columbia.edu/content/charles-hailey", "Research Summary": null, "Research Embedding": null}, {"Name": "Colin Hill", "Title": "Assistant Professor, Physics", "url": "https://www.astro.columbia.edu/content/colin-hill", "Research Summary": null, "Research Embedding": null}, {"Name": "Lam Hui", "Title": "Professor, Physics", "url": "https://www.astro.columbia.edu/content/lam-hui", "Research Summary": null, "Research Embedding": null}, {"Name": "Laura Kay", "Title": "Professor, Physics & Astronomy, Barnard", "url": "https://www.astro.columbia.edu/content/laura-kay", "Research Summary": null, "Research Embedding": null}, {"Name": "Janna Levin", "Title": "Professor, Physics & Astronomy, Barnard", "url": "https://www.astro.columbia.edu/content/janna-levin", "Research Summary": null, "Research Embedding": null}, {"Name": "Yuri Levin", "Title": "Professor, Physics", "url": "https://www.astro.columbia.edu/content/yuri-levin", "Research Summary": null, "Research Embedding": null}, {"Name": "Mordecai-Mark Mac Low", "Title": "Adjunct Professor, Astronomy; Professor and Curator, AMNH", "url": "https://www.astro.columbia.edu/content/mordecai-mark-mac-low", "Research Summary": null, "Research Embedding": null}, {"Name": "Szabolcs M\u00e1rka", "Title": "Walter O. LeCroy, Jr. Professor, Physics", "url": "https://www.astro.columbia.edu/content/szabolcs-marka", "Research Summary": null, "Research Embedding": null}, {"Name": "Morgan May", "Title": "Adjunct Professor, Physics", "url": "https://www.astro.columbia.edu/content/morgan-may", "Research Summary": null, "Research Embedding": null}, {"Name": "Brian David Metzger", "Title": "Professor, Physics", "url": "https://www.astro.columbia.edu/content/brian-david-metzger", "Research Summary": null, "Research Embedding": null}, {"Name": "Reshmi Mukherjee", "Title": "Professor, Physics & Astronomy, Barnard", "url": "https://www.astro.columbia.edu/content/reshmi-mukherjee", "Research Summary": null, "Research Embedding": null}, {"Name": "Rebecca Oppenheimer", "Title": "Adjunct Professor, Astronomy; Professor and Curator, AMNH", "url": "https://www.astro.columbia.edu/content/rebecca-oppenheimer", "Research Summary": null, "Research Embedding": null}, {"Name": "Michael Shara", "Title": "Adjunct Professor, Astronomy; Professor and Curator, AMNH", "url": "https://www.astro.columbia.edu/content/michael-shara", "Research Summary": null, "Research Embedding": null}, {"Name": "Statia Cook", "Title": "Columbia Science Fellow, Astronomy", "url": "https://www.astro.columbia.edu/content/statia-cook", "Research Summary": null, "Research Embedding": null}, {"Name": "Nicholas Luber", "Title": "Lecturer, Astronomy", "url": "https://www.astro.columbia.edu/content/nicholas-luber", "Research Summary": null, "Research Embedding": null}, {"Name": "Amanda Quirk", "Title": "Lecturer, Astronomy", "url": "https://www.astro.columbia.edu/content/amanda-quirk", "Research Summary": null, "Research Embedding": null}]